README.md
setup.py
pybem/__init__.py
pybem/block.py
pybem/element.py
pybem/node.py
pybem.egg-info/PKG-INFO
pybem.egg-info/SOURCES.txt
pybem.egg-info/dependency_links.txt
pybem.egg-info/top_level.txt