Metadata-Version: 1.2
Name: pybem
Version: 0.1.2
Summary: This package provides helpers for BEM classes generation
Home-page: https://github.com/knaydenov/pybem
Author: Klim Naydenov
Author-email: knaydenov@gmail.com
License: UNKNOWN
Platform: UNKNOWN
Requires-Python: >=3.4
